py_sfp_eeprom-0.1.3.dist-info/licenses/LICENSE
sfp_eeprom/__init__.py
sfp_eeprom/eeprom.py
py_sfp_eeprom-0.1.3.dist-info/METADATA
py_sfp_eeprom-0.1.3.dist-info/WHEEL
py_sfp_eeprom-0.1.3.dist-info/top_level.txt
py_sfp_eeprom-0.1.3.dist-info/RECORD
