Metadata-Version: 2.4
Name: py-sfp-eeprom
Version: 0.1.3
Summary: Python library for creating and manipulating SFP EEPROM data
Home-page: https://github.com/Better-Internet-Ltd/py-sfp-eeprom
Author: py-sfp-eeprom contributors
License: MIT
Project-URL: Homepage, https://github.com/Better-Internet-Ltd/py-sfp-eeprom
Project-URL: Repository, https://github.com/Better-Internet-Ltd/py-sfp-eeprom
Keywords: sfp,eeprom,fiber,optics,transceiver,sff-8472
Classifier: Development Status :: 4 - Beta
Classifier: Intended Audience :: Developers
Classifier: Intended Audience :: Telecommunications Industry
Classifier: License :: OSI Approved :: MIT License
Classifier: Programming Language :: Python :: 3
Classifier: Programming Language :: Python :: 3.7
Classifier: Programming Language :: Python :: 3.8
Classifier: Programming Language :: Python :: 3.9
Classifier: Programming Language :: Python :: 3.10
Classifier: Programming Language :: Python :: 3.11
Classifier: Programming Language :: Python :: 3.12
Classifier: Topic :: Software Development :: Libraries :: Python Modules
Classifier: Topic :: System :: Hardware
Requires-Python: >=3.7
License-File: LICENSE
Dynamic: home-page
Dynamic: license-file
Dynamic: requires-python
